{"status": "OK", "response": {"docs": [{"score": 2.4079074e-05, "web_url": "https://www.nytimes.com/video/movies/100000004371253/someplace-with-a-mountain.html", "section_name": "Movies"}, {"score": 2.405103e-05, "web_url": "https://www.legacy.com/Link.asp?I=LS000180116202", "section_name": "Paid Death Notices"}, {"score": 2.3824923e-05, "web_url": "https://query.nytimes.com/gst/fullpage.html?res=9C0DEEDB133AF937A15756C0A9609D8B63", "section_name": "Paid Death Notices"}, {"score": 2.3719582e-05, "web_url": "https://www.legacy.com/Link.asp?I=LS000180091601", "section_name": "Paid Death Notices"}, {"score": 2.3392817e-05, "web_url": "https://www.nytimes.com/video/movies/100000004355677/mine-games.html", "section_name": "Movies"}, {"score": 2.2901018e-05, "web_url": "https://www.nytimes.com/video/movies/100000004348526/bratz-rock-angelz.html", "section_name": "Movies"}, {"score": 2.258398e-05, "web_url": "https://www.nytimes.com/video/movies/100000004338267/pod.html", "section_name": "Movies"}, {"score": 2.253566e-05, "web_url": "https://www.nytimes.com/video/movies/100000004407394/fritz-lang.html", "section_name": "Movies"}, {"score": 2.2399074e-05, "web_url": "https://query.nytimes.com/gst/fullpage.html?res=9A04E2DE133AF936A25756C0A9609D8B63", "section_name": "Paid Death Notices"}, {"score": 2.236745e-05, "web_url": "https://www.nytimes.com/video/movies/100000004393384/animus.html", "section_name": "Movies"}], "meta": {"hits": 1313, "time": 22, "offset": 380}}, "copyright": "Copyright (c) 2018 The New York Times Company. All Rights Reserved."}