{"status": "OK", "response": {"docs": [{"score": 1.1298219e-05, "web_url": "https://www.nytimes.com/2016/06/17/sports/soccer/euro-2016-copa-america-player-fatigue.html", "section_name": "Sports"}, {"score": 1.1293835e-05, "web_url": "https://www.nytimes.com/2016/06/18/world/europe/syria-refugees-baby-surgery-barcelona.html", "section_name": "World"}, {"score": 1.1242985e-05, "web_url": "https://www.nytimes.com/2016/06/17/movies/2016-sundance-film-festival-short-film-tour-review.html", "section_name": "Movies"}, {"score": 1.1228508e-05, "web_url": "https://www.legacy.com/Link.asp?I=LS000180345477", "section_name": "Paid Death Notices"}, {"score": 1.120658e-05, "web_url": "https://www.nytimes.com/2016/05/15/fashion/weddings/alice-lin-helene-vincent.html", "section_name": "Fashion & Style"}, {"score": 1.1138715e-05, "web_url": "https://query.nytimes.com/gst/fullpage.html?res=9E00E4DB103AF935A25755C0A9609D8B63", "section_name": "Paid Death Notices"}, {"score": 1.1068004e-05, "web_url": "https://query.nytimes.com/gst/fullpage.html?res=9506E1DF103AF935A35755C0A9609D8B63", "section_name": "Paid Death Notices"}, {"score": 1.098799e-05, "web_url": "https://www.nytimes.com/2016/06/14/business/dealbook/handful-of-advisers-behind-microsofts-deal-for-linkedin.html", "section_name": "Business Day"}, {"score": 1.0979549e-05, "web_url": "https://www.legacy.com/Link.asp?I=LS000180221908", "section_name": "Paid Death Notices"}, {"score": 1.0967556e-05, "web_url": "https://query.nytimes.com/gst/fullpage.html?res=9906E5DF103AF936A35755C0A9609D8B63", "section_name": "Paid Death Notices"}], "meta": {"hits": 1313, "time": 16, "offset": 480}}, "copyright": "Copyright (c) 2018 The New York Times Company. All Rights Reserved."}